aklm/__init__.py
aklm/config.py
aklm/manager.py
aklm-1.0.1.dist-info/METADATA
aklm-1.0.1.dist-info/WHEEL
aklm-1.0.1.dist-info/entry_points.txt
aklm-1.0.1.dist-info/licenses/LICENSE
aklm-1.0.1.dist-info/RECORD
