Metadata-Version: 2.4
Name: aklm
Version: 1.0.1
Summary: Automatic Keyboard Layout Manager for i3wm
License: MIT
License-File: LICENSE
Keywords: i3,keyboard,layout
Author: Adrien Oliva
Author-email: aoliva@yapbreak.fr
Requires-Python: >=3.10,<4.0
Classifier: Environment :: Console
Classifier: License :: OSI Approved :: MIT License
Classifier: Programming Language :: Python
Classifier: Programming Language :: Python :: 3
Classifier: Programming Language :: Python :: 3.10
Classifier: Programming Language :: Python :: 3.11
Classifier: Programming Language :: Python :: 3.12
Classifier: Programming Language :: Python :: 3.13
Classifier: Programming Language :: Python :: 3.14
Requires-Dist: i3ipc (>=2.2.1,<3.0.0)
Project-URL: Documentation, https://aoliva.pages.yapbreak.fr/aklm/docs
Project-URL: Homepage, https://git.yapbreak.fr/aoliva/aklm
Project-URL: Issues, https://git.yapbreak.fr/aoliva/aklm/-/issues
Project-URL: Repository, https://git.yapbreak.fr/aoliva/aklm
